pharmpy/__init__.py
pharmpy/__main__.py
pharmpy/cli.py
pharmpy/config.py
pharmpy/visualization.py
pharmpy/basic/__init__.py
pharmpy/basic/expr.py
pharmpy/basic/matrix.py
pharmpy/basic/unit.py
pharmpy/deps/__init__.py
pharmpy/deps/altair.py
pharmpy/deps/rich.py
pharmpy/deps/scipy.py
pharmpy/deps/sympy_printing.py
pharmpy/internals/__init__.py
pharmpy/internals/code_generator.py
pharmpy/internals/df.py
pharmpy/internals/immutable.py
pharmpy/internals/math.py
pharmpy/internals/sort.py
pharmpy/internals/unicode.py
pharmpy/internals/ds/__init__.py
pharmpy/internals/ds/ordered_set.py
pharmpy/internals/example_models/moxo.csv
pharmpy/internals/example_models/moxo.mod
pharmpy/internals/example_models/pheno.cov
pharmpy/internals/example_models/pheno.datainfo
pharmpy/internals/example_models/pheno.dta
pharmpy/internals/example_models/pheno.ext
pharmpy/internals/example_models/pheno.lst
pharmpy/internals/example_models/pheno.mod
pharmpy/internals/example_models/pheno.phi
pharmpy/internals/example_models/pheno.tab
pharmpy/internals/example_models/pheno_linear.dta
pharmpy/internals/example_models/pheno_linear.ext
pharmpy/internals/example_models/pheno_linear.lst
pharmpy/internals/example_models/pheno_linear.mod
pharmpy/internals/example_models/pheno_linear.phi
pharmpy/internals/expr/__init__.py
pharmpy/internals/expr/assumptions.py
pharmpy/internals/expr/eval.py
pharmpy/internals/expr/funcs.py
pharmpy/internals/expr/leaves.py
pharmpy/internals/expr/matrix.py
pharmpy/internals/expr/ode.py
pharmpy/internals/expr/parse.py
pharmpy/internals/expr/subs.py
pharmpy/internals/expr/tree.py
pharmpy/internals/fn/__init__.py
pharmpy/internals/fn/signature.py
pharmpy/internals/fn/type.py
pharmpy/internals/fs/__init__.py
pharmpy/internals/fs/cwd.py
pharmpy/internals/fs/lock.py
pharmpy/internals/fs/path.py
pharmpy/internals/fs/symlink.py
pharmpy/internals/fs/tmp.py
pharmpy/internals/graph/directed/__init__.py
pharmpy/internals/graph/directed/connected_components.py
pharmpy_core-1.12.0.dist-info/licenses/LICENSE
pharmpy_core-1.12.0.dist-info/licenses/LICENSE.LESSER
pharmpy_core-1.12.0.dist-info/METADATA
pharmpy_core-1.12.0.dist-info/WHEEL
pharmpy_core-1.12.0.dist-info/entry_points.txt
pharmpy_core-1.12.0.dist-info/top_level.txt
pharmpy_core-1.12.0.dist-info/RECORD
