Metadata-Version: 2.4
Name: pharmpy-core
Version: 1.12.0
Summary: Pharmacometric modeling
Author-email: Rikard Nordgren <rikard.nordgren@uu.se>
License-Expression: LGPL-3.0-or-later
Project-URL: Homepage, https://pharmpy.github.io
Project-URL: Documentation, https://pharmpy.github.io
Project-URL: Issues, https://github.com/pharmpy/pharmpy/issues
Project-URL: Repository, https://github.com/pharmpy/pharmpy
Project-URL: Changelog, https://pharmpy.github.io/latest/changelog.html
Keywords: pharmacometrics
Classifier: Development Status :: 5 - Production/Stable
Classifier: Intended Audience :: Science/Research
Classifier: Intended Audience :: Developers
Classifier: Operating System :: POSIX
Classifier: Operating System :: MacOS
Classifier: Operating System :: Unix
Classifier: Operating System :: Microsoft :: Windows
Classifier: Programming Language :: Python
Classifier: Programming Language :: Python :: 3 :: Only
Classifier: Programming Language :: Python :: 3.11
Classifier: Programming Language :: Python :: 3.12
Classifier: Programming Language :: Python :: 3.13
Classifier: Programming Language :: Python :: 3.14
Classifier: Programming Language :: Python :: Implementation :: CPython
Classifier: Topic :: Scientific/Engineering
Requires-Python: >=3.11
License-File: LICENSE
License-File: LICENSE.LESSER
Requires-Dist: lark>=1.1.7
Requires-Dist: sympy>=1.9
Requires-Dist: symengine>=0.13.0
Requires-Dist: pandas!=2.1.0,>=1.4
Requires-Dist: numexpr>=2.7.0
Requires-Dist: altair>=6.0.0
Requires-Dist: itables>=2.4.0
Requires-Dist: jsonschema>=3.1.0
Requires-Dist: sphinx>=2.2.0
Requires-Dist: csscompressor>=0.9.5
Requires-Dist: beautifulsoup4>=4.13.0
Requires-Dist: lxml>=4.4.0
Requires-Dist: numpy>=1.17
Requires-Dist: scipy>=1.4.0
Requires-Dist: dask>=2024.2.1
Requires-Dist: distributed>=2024.2.1
Requires-Dist: networkx>=2.3
Requires-Dist: appdirs>=1.4.4
Requires-Dist: rich>=4.2.0
Requires-Dist: jupyter-sphinx>=0.2.0
Requires-Dist: ipykernel>=5.4.0
Requires-Dist: statsmodels>=0.14.5
Provides-Extra: nlmixr
Requires-Dist: pyreadr>=0.5.3; extra == "nlmixr"
Dynamic: license-file
